scrapekit/__init__.py
scrapekit/common/__init__.py
scrapekit/common/user-agents/user-agents.json
scrapekit/ipburger/__init__.py
scrapekit-0.4.3.dist-info/WHEEL
scrapekit-0.4.3.dist-info/METADATA
scrapekit-0.4.3.dist-info/RECORD
