Metadata-Version: 2.1
Name: scrapekit
Version: 0.4.3
Summary: Modular scraping convenience framework written in Python.
Home-page: https://bitbucket.org/omniviant/scrapekit/
Keywords: Web scraping,Scraping,IP Burger,Proxy
Author: C. W.
Author-email: c@omniviant.com
Maintainer: C. W.
Maintainer-email: c@omniviant.com
Requires-Python: >=3.9,<4.0
Classifier: Programming Language :: Python :: 3
Classifier: Programming Language :: Python :: 3.10
Classifier: Programming Language :: Python :: 3.9
Requires-Dist: requests (>=2.27.1,<3.0.0)
Project-URL: Repository, https://bitbucket.org/omniviant/scrapekit/
